pycdoexpr/__init__.py
pycdoexpr/util.py
test/__init__.py
test/test_pycdoexpr.py
pycdoexpr-0.0.2.dist-info/METADATA
pycdoexpr-0.0.2.dist-info/WHEEL
pycdoexpr-0.0.2.dist-info/top_level.txt
pycdoexpr-0.0.2.dist-info/RECORD
