Metadata-Version: 2.1
Name: pycdoexpr
Version: 0.0.2
Summary: A Python package helps to generate complicated cdo expr(computing expression) in pythonic way
Home-page: https://github.com/blizhan/pycdoexpr
Author: blizhan
Author-email: blizhan@icloud.com
Classifier: Programming Language :: Python :: 3
Requires-Python: >=3.7
Requires-Dist: numpy
Requires-Dist: binarytree
